flake8_no_pep420/__init__.py
flake8_no_pep420/py.typed
flake8_no_pep420-2.9.0.dist-info/licenses/LICENSE
flake8_no_pep420-2.9.0.dist-info/METADATA
flake8_no_pep420-2.9.0.dist-info/WHEEL
flake8_no_pep420-2.9.0.dist-info/entry_points.txt
flake8_no_pep420-2.9.0.dist-info/top_level.txt
flake8_no_pep420-2.9.0.dist-info/RECORD
